sokobanpy/__init__.py
sokobanpy/sokobanpy.py
sokobanpy-1.3.0.dist-info/METADATA
sokobanpy-1.3.0.dist-info/WHEEL
sokobanpy-1.3.0.dist-info/top_level.txt
sokobanpy-1.3.0.dist-info/RECORD
