Metadata-Version: 2.4
Name: sokobanpy
Version: 1.3.0
Summary: Sokoban in Python.
Author-email: Quan Lin <jacklinquan@gmail.com>
Project-URL: Homepage, https://github.com/jacklinquan/sokobanpy
Keywords: sokoban
Classifier: License :: OSI Approved :: MIT License
Classifier: Programming Language :: Python :: 3
Requires-Python: >=3.7
Provides-Extra: dev
Requires-Dist: black; extra == "dev"
Requires-Dist: pytest; extra == "dev"
Requires-Dist: mkdocs; extra == "dev"
Requires-Dist: mkdocstrings-python; extra == "dev"
